{
  "AOD": "Anticoagulant oral direct",
  "AVK": "Antivitamine K",
  "INR": "Ratio normalisé international",
  "HIC": "Hémorragie intracrânienne",
  "AVC": "Accident vasculaire cérébral",
  "TCC": "Traumatisme craniocérébral",
  "DAPT": "Double antiagrégation plaquettaire",
  "ASA": "Acide acétylsalicylique",
  "AAS": "Acide acétylsalicylique",
  "P2Y12": "Récepteur plaquettaire ciblé par certains antiplaquettaires",
  "ECG": "Électrocardiogramme",
  "QT": "Intervalle QT à l’électrocardiogramme",
  "FC": "Fréquence cardiaque",
  "PA": "Pression artérielle",
  "TA": "Tension artérielle",
  "FA": "Fibrillation auriculaire",
  "HTA": "Hypertension artérielle",
  "IC": "Insuffisance cardiaque",
  "CV": "Cardiovasculaire",
  "AV": "Auriculo-ventriculaire",
  "BAV": "Bloc auriculo-ventriculaire",
  "FR": "Fréquence respiratoire",
  "SpO2": "Saturation pulsée en oxygène",
  "BPCO": "Bronchopneumopathie chronique obstructive",
  "MPOC": "Maladie pulmonaire obstructive chronique",
  "PRN": "Au besoin",
  "IR": "Insuffisance rénale",
  "IRC": "Insuffisance rénale chronique",
  "IRA": "Insuffisance rénale aiguë",
  "AINS": "Anti-inflammatoires non stéroïdiens",
  "GI": "Gastro-intestinal",
  "SCA": "Syndrome coronarien aigu",
  "SNC": "Système nerveux central",
  "OTC": "En vente libre",
  "IM": "Infarctus du myocarde",
  "GLP-1": "Agoniste du GLP-1",
  "DPP-4": "Inhibiteur de la DPP-4",
  "SGLT2": "Inhibiteur du SGLT2",
  "ISRS": "Inhibiteur sélectif de la recapture de la sérotonine",
  "IRSN": "Inhibiteur de la recapture de la sérotonine et de la noradrénaline",
  "IEC": "Inhibiteur de l’enzyme de conversion",
  "ARA": "Antagoniste des récepteurs de l’angiotensine",
  "ARNI": "Inhibiteur des récepteurs de l’angiotensine et de la néprilysine",
  "DHP": "Dihydropyridine",
  "non-DHP": "Inhibiteur calcique non dihydropyridine",
  "α2": "Agoniste alpha-2 central",
  "HBP": "Hyperplasie bénigne de la prostate",
  "LUTS": "Symptômes du bas appareil urinaire",
  "HBPM": "Héparine de bas poids moléculaire",
  "TEV": "Thromboembolie veineuse",
  "TVP": "Thrombose veineuse profonde",
  "EP": "Embolie pulmonaire",
  "TAO": "Traitement agoniste opioïde",
  "TUO": "Trouble lié à l’usage d’opioïdes",
  "NTG": "Nitroglycérine",
  "HCTZ": "Hydrochlorothiazide",
  "APAP": "Acétaminophène",
  "IPP": "Inhibiteur de la pompe à protons",
  "ICS": "Corticostéroïde inhalé",
  "LABA": "Bêta-2 agoniste à longue action",
  "LAMA": "Antagoniste muscarinique à longue action",
  "SAMA": "Antagoniste muscarinique à courte action",
  "TDAH": "Trouble déficitaire de l’attention avec ou sans hyperactivité",
  "ITU": "Infection urinaire",
  "RGO": "Reflux gastro-œsophagien",
  "IV": "Intraveineux",
  "SL": "Sublingual",
  "SR": "Libération soutenue",
  "XL": "Libération prolongée",
  "XR": "Libération prolongée",
  "ER": "Libération prolongée",
  "TMO": "Trouble musculosquelettique",
  "RAU": "Rétention aiguë urinaire (incapacité d’uriner, vessie pleine douloureuse)",
  "GV": "Globe vésical (rétention complète avec distension palpable)"
}
